{
  "project_info": {
    "project_number": "620337587532",
    "firebase_url": "https://chat-clean-default-rtdb.firebaseio.com",
    "project_id": "chat-clean",
    "storage_bucket": "chat-clean.appspot.com"
  },
  "client": [
    {
      "client_info": {
        "mobilesdk_app_id": "1:620337587532:android:cd19d9df945ffdab129be9",
        "android_client_info": {
          "package_name": "com.example.app_chat"
        }
      },
      "oauth_client": [
        {
          "client_id": "620337587532-3lqh97vgkbkfskue0eprkkej9gfcgft4.apps.googleusercontent.com",
          "client_type": 3
        }
      ],
      "api_key": [
        {
          "current_key": "AIzaSyB9002LkQmyx4mdCB-sxGjZVkP-5HVjPFg"
        }
      ],
      "services": {
        "appinvite_service": {
          "other_platform_oauth_client": [
            {
              "client_id": "620337587532-3lqh97vgkbkfskue0eprkkej9gfcgft4.apps.googleusercontent.com",
              "client_type": 3
            },
            {
              "client_id": "620337587532-1lp779kjubnpo8n3rd8lpfh5k0do15g6.apps.googleusercontent.com",
              "client_type": 2,
              "ios_info": {
                "bundle_id": "com.example.appChat"
              }
            }
          ]
        }
      }
    }
  ],
  "configuration_version": "1"
}